{
    "author": "FreeSewing.org",
    "type": "curatedMeasurementsSet",
    "about": "Contains measurements in mm as well as metadata",
    "id": 3,
    "createdAt": "2023-10-19T13:29:01.288Z",
    "height": 150,
    "nameDe": "Vanessa",
    "nameEn": "Vanessa",
    "nameEs": "Vanessa",
    "nameFr": "Vanessa",
    "nameNl": "Vanessa",
    "nameUk": "Vanessa",
    "notesDe": "56 kg",
    "notesEn": "56 kg",
    "notesEs": "56 kg",
    "notesFr": "56 kg",
    "notesNl": "56 kg",
    "notesUk": "56 kg",
    "tags": {},
    "updatedAt": "2023-10-22T14:07:40.672Z",
    "published": true,
    "measurements": {
        "ankle": 220,
        "biceps": 280,
        "bustFront": 540,
        "bustPointToUnderbust": 90,
        "bustSpan": 180,
        "chest": 940,
        "crossSeam": 620,
        "crossSeamFront": 290,
        "crotchDepth": 200,
        "head": 540,
        "heel": 280,
        "highBust": 890,
        "highBustFront": 430,
        "hips": 860,
        "hpsToBust": 260,
        "hpsToWaistBack": 380,
        "hpsToWaistFront": 430,
        "inseam": 680,
        "knee": 360,
        "neck": 330,
        "seat": 980,
        "seatBack": 510,
        "shoulderSlope": 9,
        "shoulderToElbow": 280,
        "shoulderToShoulder": 350,
        "shoulderToWrist": 520,
        "underbust": 810,
        "upperLeg": 580,
        "waist": 780,
        "waistBack": 360,
        "waistToFloor": 890,
        "waistToHips": 90,
        "waistToKnee": 500,
        "waistToSeat": 200,
        "waistToUnderbust": 100,
        "waistToUpperLeg": 250,
        "wrist": 160,
        "waistToArmpit": 210
    }
}